Basic modules/full_adder_s/full_adder_s.v
// Code for a sequential full adder circuit

module full_adder_s (a, b, cin, clk, sum, cout);
input a, b, cin, clk;
output reg cout, sum;
always @(posedge clk) begin
    sum = a ^ b ^ cin;
    cout = (a & b) | (b & cin) | (a & cin);
end
endmodule

Basic modules/full_adder_s/full_adder_s_tb.v
`include "full_adder_s.v"
`timescale 1ns/1ps

module full_adder_s_tb;
    reg a, b, cin, clk;
    wire cout, sum;

    // Instantiate the full adder
    full_adder_s add1(a, b, cin, clk, sum, cout);

    // Clock generation: 10ns period (5ns high, 5ns low)
    initial begin
        clk = 0;
        forever #5 clk = ~clk;
    end

    // Stimulus and VCD generation
    initial begin
        // Create VCD file for waveform output
        $dumpfile("full_adder_s.vcd");
        $dumpvars(0, full_adder_s_tb);

        $display("starting tests....");
        // Apply test vectors
        a = 0; b = 0; cin = 0; #10;
        a = 0; b = 0; cin = 1; #10;
        a = 0; b = 1; cin = 0; #10;
        a = 0; b = 1; cin = 1; #10;
        $display("midway....");
        a = 1; b = 0; cin = 0; #10;
        a = 1; b = 0; cin = 1; #10;
        a = 1; b = 1; cin = 0; #10;
        a = 1; b = 1; cin = 1; #10;
        $display("tests done....");
        // End simulation
        $finish;
    end

endmodule

Basic modules/full_adder_s/full_adder_s.vcd
$date
	Sun Mar 30 19:59:29 2025
$end
$version
	Icarus Verilog
$end
$timescale
	1ps
$end
$scope module full_adder_s_tb $end
$var wire 1 ! sum $end
$var wire 1 " cout $end
$var reg 1 # a $end
$var reg 1 $ b $end
$var reg 1 % cin $end
$var reg 1 & clk $end
$scope module add1 $end
$var wire 1 # a $end
$var wire 1 $ b $end
$var wire 1 % cin $end
$var wire 1 & clk $end
$var reg 1 " cout $end
$var reg 1 ! sum $end
$upscope $end
$upscope $end
$enddefinitions $end
$comment Show the parameter values. $end
$dumpall
$end
#0
$dumpvars
0&
0%
0$
0#
x"
x!
$end
#5000
0"
0!
1&
#10000
0&
1%
#15000
1!
1&
#20000
0&
0%
1$
#25000
1&
#30000
0&
1%
#35000
1"
0!
1&
#40000
0&
0%
0$
1#
#45000
0"
1!
1&
#50000
0&
1%
#55000
1"
0!
1&
#60000
0&
0%
1$
#65000
1&
#70000
0&
1%
#75000
1!
1&
