Basic modules/full_adder/full_adder.v
module full_adder (a, b, cin, sum, cout);
input a, b, cin;
output sum, cout;
assign sum = a ^ b ^ cin;
assign cout = (a & b) | (b & cin) | (cin & a);
endmodule

Basic modules/full_adder/full_adder_tb.v
`include "full_adder.v"

module full_adder_tb;
    reg a, b, cin;
    wire sum, cout;

    full_adder add1(a, b, cin, sum, cout);
    initial begin
        $dumpfile("full_adder.vcd");
        $dumpvars(0, full_adder_tb);
        a = 0; b = 0; cin = 0; #10;
        a = 0; b = 0; cin = 1; #10;
        a = 0; b = 1; cin = 0; #10;
        a = 0; b = 1; cin = 1; #10;
        a = 1; b = 0; cin = 0; #10;
        a = 1; b = 0; cin = 1; #10;
        a = 1; b = 1; cin = 0; #10;
        a = 1; b = 1; cin = 1; #10;
        $finish;
    end
endmodule

Basic modules/full_adder/full_adder.vcd
$date
	Sun Mar 30 18:46:52 2025
$end
$version
	Icarus Verilog
$end
$timescale
	1s
$end
$scope module full_adder_tb $end
$var wire 1 ! sum $end
$var wire 1 " cout $end
$var reg 1 # a $end
$var reg 1 $ b $end
$var reg 1 % cin $end
$scope module add1 $end
$var wire 1 # a $end
$var wire 1 $ b $end
$var wire 1 % cin $end
$var wire 1 " cout $end
$var wire 1 ! sum $end
$upscope $end
$upscope $end
$enddefinitions $end
$comment Show the parameter values. $end
$dumpall
$end
#0
$dumpvars
0%
0$
0#
0"
0!
$end
#10
1!
1%
#20
0%
1$
#30
1"
0!
1%
#40
0"
1!
0%
0$
1#
#50
1"
0!
1%
#60
0%
1$
#70
1!
1%
